Pixel Wise Filters/pixel_wise_filter.sv
`timescale 1ns/1ps

// Pixel-wise filter module
// Each pixel is processed independently, based only on its value and external params.

module pixel_wise_filter 
#(
    parameter int NUM_STATES   = 4,
    parameter int BITS         = 8,   // pixel bit depth
    parameter int DEPTHVAL     = 256, // 2^BITS
    parameter int STEP_SIZE    = (256 * (1<<8)) / 200, // scale so BPM=200 gives brightness ≈ 255
    parameter int NUM_FILTERS  = 2,
    parameter int MIN_BPM      = 40,
    parameter int MAX_BPM      = 200
)
(
    input  logic                  clk,
    input  logic                  reset,

    input  logic [BITS-1:0]       pix_in,       
    input  logic                  valid_in,
    output logic                  module_ready,

    input  logic                  filter_enable,
    input  logic                  filter_mode,  // 0 = threshold, 1 = additive
    input  logic [$clog2(MAX_BPM+1)-1:0] BPM_estimate, 

    output logic [BITS-1:0]       pix_out,
    input  logic                  output_ready,
    output logic                  valid_out,
    output logic [BITS-1:0]       brightness,
    output logic [23:0]           brightness_mult
);

assign module_ready = output_ready;

logic [BITS:0] pix_bright_addition;

// Scale brightness based on BPM
assign brightness_mult = (STEP_SIZE * BPM_estimate) >> 8;
assign brightness      = (brightness_mult > 255) ? 8'd255 : brightness_mult[7:0];

always_comb begin
    if (module_ready && valid_in && filter_enable) begin
        if (filter_mode) begin
            // additive / averaging
            pix_bright_addition = (pix_in + brightness) >> 1;
            pix_out = pix_bright_addition;
        end else begin
            // threshold
            if (pix_in <= brightness)
                pix_out = 0;
            else
                pix_out = pix_in;
        end
    end else begin
        pix_out = 0;
    end
end

assign valid_out = module_ready && valid_in && filter_enable;

endmodule

Pixel Wise Filters/top_level_filters.sv
`timescale 1ns/1ps

// Simple top-level wrapper that instantiates pixel_wise_filter
// You can add more filters here if needed.

module top_level_filters (
    input  logic        clk,
    input  logic        reset,
    input  logic [7:0]  pix_in,
    input  logic        valid_in,
    output logic        module_ready,
    input  logic        filter_enable,
    input  logic        filter_mode,
    input  logic [7:0]  BPM_estimate,
    output logic [7:0]  pix_out,
    output logic        valid_out,
    input  logic        output_ready,
    output logic [7:0]  brightness
);

  logic [23:0] brightness_mult;

  pixel_wise_filter #(
    .BITS(8),
    .MAX_BPM(200)
  ) u_pixel_filter (
    .clk(clk),
    .reset(reset),
    .pix_in(pix_in),
    .valid_in(valid_in),
    .module_ready(module_ready),
    .filter_enable(filter_enable),
    .filter_mode(filter_mode),
    .BPM_estimate(BPM_estimate),
    .pix_out(pix_out),
    .output_ready(output_ready),
    .valid_out(valid_out),
    .brightness(brightness),
    .brightness_mult(brightness_mult)
  );

endmodule

Pixel Wise Filters/pixel_wise_filters_tb.sv
`timescale 1ns/1ps

// ===========================================================
// Testbench for top_level_filters
// Demonstrates: 
//  - Clock + reset generation
//  - DUT instantiation
//  - Stimulus driving (pix_in, BPM, modes)
//  - Output monitoring with $display
//  - VCD dumping for GTKWave (viewing waveforms)
// ===========================================================

module pixel_wise_filters_tb;

  // ------------------------------
  // Clock & Reset
  // ------------------------------
  logic clk = 0;
  logic reset = 1;

  // Clock generator (25 MHz -> 40ns period)
  always #20 clk = ~clk;

  // Reset pulse
  initial begin
    repeat(5) @(posedge clk);
    reset = 0;
  end

  // ------------------------------
  // DUT connections
  // ------------------------------
  logic [7:0] pix_in;
  logic       valid_in;
  logic       module_ready;
  logic       filter_enable;
  logic       filter_mode;
  logic [7:0] BPM_estimate;
  logic [7:0] pix_out;
  logic       valid_out;
  logic       output_ready;
  logic [7:0] brightness;
  logic [23:0] pix_bright_addition;

  // Instantiate the design under test
  top_level_filters dut (
    .clk(clk),
    .reset(reset),
    .pix_in(pix_in),
    .valid_in(valid_in),
    .module_ready(module_ready),
    .filter_enable(filter_enable),
    .filter_mode(filter_mode),
    .BPM_estimate(BPM_estimate),
    .pix_out(pix_out),
    .valid_out(valid_out),
    .output_ready(output_ready),
    .brightness(brightness)
  );

  // ------------------------------
  // Stimulus
  // ------------------------------
  initial begin
    // Default values
    pix_in        = 0;
    valid_in      = 0;
    filter_enable = 1;
    filter_mode   = 0;   // 0 = threshold, 1 = additive
    BPM_estimate  = 200;
    output_ready  = 1;

    // Wait until reset is released
    @(negedge reset);

    // Sweep pixels down and adjust BPM mid-stream
    for (int bpm = 200; bpm >= 56; bpm -= 16) begin
      BPM_estimate = bpm;
      for (int i = 0; i < 10; i++) begin
        @(posedge clk);
        pix_in   = 255 - i*25;
        valid_in = 1;
      end
      valid_in = 0;
      #200;
    end

    // Switch to average mode
    filter_mode = 1;
    BPM_estimate = 200;
    for (int bpm = 200; bpm >= 56; bpm -= 16) begin
      BPM_estimate = bpm;
      for (int i = 0; i < 10; i++) begin
        @(posedge clk);
        pix_in   = 255 - i*25;
        valid_in = 1;
      end
      valid_in = 0;
      #200;
    end

    #200 $finish;
  end

  // ------------------------------
  // Output Monitoring
  // ------------------------------
  always @(posedge clk) begin
    if (valid_out)
      $display("t=%0t | pix_in=%0d | BPM=%0d | brightness=%0d | brightness average=%0d | mode=%0d | pix_out=%0d",
               $time, pix_in, BPM_estimate, brightness, pix_bright_addition, filter_mode, pix_out);
  end

    assign pix_bright_addition = (pix_in + brightness) >> 1;
  // ------------------------------
  // Waveform Dumping
  // ------------------------------
  initial begin
    $dumpfile("tb.vcd");
    $dumpvars(0, pixel_wise_filters_tb);
  end

endmodule

Pixel Wise Filters/tb.vcd
$date
	Thu Sep 25 13:47:49 2025
$end
$version
	Icarus Verilog
$end
$timescale
	1ps
$end
$scope module pixel_wise_filters_tb $end
$var wire 1 ! valid_out $end
$var wire 8 " pix_out [7:0] $end
$var wire 24 # pix_bright_addition [23:0] $end
$var wire 1 $ module_ready $end
$var wire 8 % brightness [7:0] $end
$var reg 8 & BPM_estimate [7:0] $end
$var reg 1 ' clk $end
$var reg 1 ( filter_enable $end
$var reg 1 ) filter_mode $end
$var reg 1 * output_ready $end
$var reg 8 + pix_in [7:0] $end
$var reg 1 , reset $end
$var reg 1 - valid_in $end
$scope module dut $end
$var wire 8 . BPM_estimate [7:0] $end
$var wire 1 ' clk $end
$var wire 1 ( filter_enable $end
$var wire 1 ) filter_mode $end
$var wire 1 * output_ready $end
$var wire 8 / pix_in [7:0] $end
$var wire 1 , reset $end
$var wire 1 - valid_in $end
$var wire 1 ! valid_out $end
$var wire 8 0 pix_out [7:0] $end
$var wire 1 $ module_ready $end
$var wire 24 1 brightness_mult [23:0] $end
$var wire 8 2 brightness [7:0] $end
$scope module u_pixel_filter $end
$var wire 8 3 BPM_estimate [7:0] $end
$var wire 1 ' clk $end
$var wire 1 ( filter_enable $end
$var wire 1 ) filter_mode $end
$var wire 1 $ module_ready $end
$var wire 1 * output_ready $end
$var wire 8 4 pix_in [7:0] $end
$var wire 1 , reset $end
$var wire 1 - valid_in $end
$var wire 1 ! valid_out $end
$var wire 24 5 brightness_mult [23:0] $end
$var wire 8 6 brightness [7:0] $end
$var reg 9 7 pix_bright_addition [8:0] $end
$var reg 8 8 pix_out [7:0] $end
$upscope $end
$upscope $end
$scope begin $ivl_for_loop0 $end
$var integer 32 9 bpm [31:0] $end
$scope begin $ivl_for_loop1 $end
$var integer 32 : i [31:0] $end
$upscope $end
$upscope $end
$scope begin $ivl_for_loop2 $end
$var integer 32 ; bpm [31:0] $end
$scope begin $ivl_for_loop3 $end
$var integer 32 < i [31:0] $end
$upscope $end
$upscope $end
$upscope $end
$enddefinitions $end
#0
$dumpvars
b0 <
b0 ;
b0 :
b0 9
b0 8
bx 7
b11111111 6
b11111111 5
b0 4
b11001000 3
b11111111 2
b11111111 1
b0 0
b0 /
b11001000 .
0-
1,
b0 +
1*
0)
1(
0'
b11001000 &
b11111111 %
1$
b1111111 #
b0 "
0!
$end
#20000
1'
#40000
0'
#60000
1'
#80000
0'
#100000
1'
#120000
0'
#140000
1'
#160000
0'
#180000
b11001000 9
0,
1'
#200000
0'
#220000
1!
b11111111 #
b1 :
1-
b11111111 +
b11111111 /
b11111111 4
1'
#240000
0'
#260000
b11110010 #
b10 :
b11100110 +
b11100110 /
b11100110 4
1'
#280000
0'
#300000
b11100110 #
b11 :
b11001101 +
b11001101 /
b11001101 4
1'
#320000
0'
#340000
b11011001 #
b100 :
b10110100 +
b10110100 /
b10110100 4
1'
#360000
0'
#380000
b11001101 #
b101 :
b10011011 +
b10011011 /
b10011011 4
1'
#400000
0'
#420000
b11000000 #
b110 :
b10000010 +
b10000010 /
b10000010 4
1'
#440000
0'
#460000
b10110100 #
b111 :
b1101001 +
b1101001 /
b1101001 4
1'
#480000
0'
#500000
b10100111 #
b1000 :
b1010000 +
b1010000 /
b1010000 4
1'
#520000
0'
#540000
b10011011 #
b1001 :
b110111 +
b110111 /
b110111 4
1'
#560000
0'
#580000
0!
b10001110 #
0-
b1010 :
b11110 +
b11110 /
b11110 4
1'
#600000
0'
#620000
1'
#640000
0'
#660000
1'
#680000
0'
#700000
1'
#720000
0'
#740000
1'
#760000
0'
#780000
b11111111 "
b11111111 0
b11111111 8
b11101011 %
b11101011 2
b11101011 6
1!
b11110101 #
b11101011 1
b11101011 5
1-
b11111111 +
b11111111 /
b11111111 4
1'
b1 :
b10111000 &
b10111000 .
b10111000 3
b10111000 9
#800000
0'
#820000
b11101000 #
b0 "
b0 0
b0 8
b10 :
b11100110 +
b11100110 /
b11100110 4
1'
#840000
0'
#860000
b11011100 #
b11 :
b11001101 +
b11001101 /
b11001101 4
1'
#880000
0'
#900000
b11001111 #
b100 :
b10110100 +
b10110100 /
b10110100 4
1'
#920000
0'
#940000
b11000011 #
b101 :
b10011011 +
b10011011 /
b10011011 4
1'
#960000
0'
#980000
b10110110 #
b110 :
b10000010 +
b10000010 /
b10000010 4
1'
#1000000
0'
#1020000
b10101010 #
b111 :
b1101001 +
b1101001 /
b1101001 4
1'
#1040000
0'
#1060000
b10011101 #
b1000 :
b1010000 +
b1010000 /
b1010000 4
1'
#1080000
0'
#1100000
b10010001 #
b1001 :
b110111 +
b110111 /
b110111 4
1'
#1120000
0'
#1140000
0!
b10000100 #
0-
b1010 :
b11110 +
b11110 /
b11110 4
1'
#1160000
0'
#1180000
1'
#1200000
0'
#1220000
1'
#1240000
0'
#1260000
1'
#1280000
0'
#1300000
1'
#1320000
0'
#1340000
b11010110 %
b11010110 2
b11010110 6
1!
b11101010 #
b11111111 "
b11111111 0
b11111111 8
b11010110 1
b11010110 5
1-
b11111111 +
b11111111 /
b11111111 4
1'
b1 :
b10101000 &
b10101000 .
b10101000 3
b10101000 9
#1360000
0'
#1380000
b11011110 #
b11100110 "
b11100110 0
b11100110 8
b10 :
b11100110 +
b11100110 /
b11100110 4
1'
#1400000
0'
#1420000
b11010001 #
b0 "
b0 0
b0 8
b11 :
b11001101 +
b11001101 /
b11001101 4
1'
#1440000
0'
#1460000
b11000101 #
b100 :
b10110100 +
b10110100 /
b10110100 4
1'
#1480000
0'
#1500000
b10111000 #
b101 :
b10011011 +
b10011011 /
b10011011 4
1'
#1520000
0'
#1540000
b10101100 #
b110 :
b10000010 +
b10000010 /
b10000010 4
1'
#1560000
0'
#1580000
b10011111 #
b111 :
b1101001 +
b1101001 /
b1101001 4
1'
#1600000
0'
#1620000
b10010011 #
b1000 :
b1010000 +
b1010000 /
b1010000 4
1'
#1640000
0'
#1660000
b10000110 #
b1001 :
b110111 +
b110111 /
b110111 4
1'
#1680000
0'
#1700000
0!
b1111010 #
0-
b1010 :
b11110 +
b11110 /
b11110 4
1'
#1720000
0'
#1740000
1'
#1760000
0'
#1780000
1'
#1800000
0'
#1820000
1'
#1840000
0'
#1860000
1'
#1880000
0'
#1900000
b11000010 %
b11000010 2
b11000010 6
1!
b11100000 #
b11111111 "
b11111111 0
b11111111 8
b11000010 1
b11000010 5
1-
b11111111 +
b11111111 /
b11111111 4
1'
b1 :
b10011000 &
b10011000 .
b10011000 3
b10011000 9
#1920000
0'
#1940000
b11010100 #
b11100110 "
b11100110 0
b11100110 8
b10 :
b11100110 +
b11100110 /
b11100110 4
1'
#1960000
0'
#1980000
b11000111 #
b11001101 "
b11001101 0
b11001101 8
b11 :
b11001101 +
b11001101 /
b11001101 4
1'
#2000000
0'
#2020000
b10111011 #
b0 "
b0 0
b0 8
b100 :
b10110100 +
b10110100 /
b10110100 4
1'
#2040000
0'
#2060000
b10101110 #
b101 :
b10011011 +
b10011011 /
b10011011 4
1'
#2080000
0'
#2100000
b10100010 #
b110 :
b10000010 +
b10000010 /
b10000010 4
1'
#2120000
0'
#2140000
b10010101 #
b111 :
b1101001 +
b1101001 /
b1101001 4
1'
#2160000
0'
#2180000
b10001001 #
b1000 :
b1010000 +
b1010000 /
b1010000 4
1'
#2200000
0'
#2220000
b1111100 #
b1001 :
b110111 +
b110111 /
b110111 4
1'
#2240000
0'
#2260000
0!
b1110000 #
0-
b1010 :
b11110 +
b11110 /
b11110 4
1'
#2280000
0'
#2300000
1'
#2320000
0'
#2340000
1'
#2360000
0'
#2380000
1'
#2400000
0'
#2420000
1'
#2440000
0'
#2460000
b10101101 %
b10101101 2
b10101101 6
1!
b11010110 #
b11111111 "
b11111111 0
b11111111 8
b10101101 1
b10101101 5
1-
b11111111 +
b11111111 /
b11111111 4
1'
b1 :
b10001000 &
b10001000 .
b10001000 3
b10001000 9
#2480000
0'
#2500000
b11001001 #
b11100110 "
b11100110 0
b11100110 8
b10 :
b11100110 +
b11100110 /
b11100110 4
1'
#2520000
0'
#2540000
b10111101 #
b11001101 "
b11001101 0
b11001101 8
b11 :
b11001101 +
b11001101 /
b11001101 4
1'
#2560000
0'
#2580000
b10110000 #
b10110100 "
b10110100 0
b10110100 8
b100 :
b10110100 +
b10110100 /
b10110100 4
1'
#2600000
0'
#2620000
b10100100 #
b0 "
b0 0
b0 8
b101 :
b10011011 +
b10011011 /
b10011011 4
1'
#2640000
0'
#2660000
b10010111 #
b110 :
b10000010 +
b10000010 /
b10000010 4
1'
#2680000
0'
#2700000
b10001011 #
b111 :
b1101001 +
b1101001 /
b1101001 4
1'
#2720000
0'
#2740000
b1111110 #
b1000 :
b1010000 +
b1010000 /
b1010000 4
1'
#2760000
0'
#2780000
b1110010 #
b1001 :
b110111 +
b110111 /
b110111 4
1'
#2800000
0'
#2820000
0!
b1100101 #
0-
b1010 :
b11110 +
b11110 /
b11110 4
1'
#2840000
0'
#2860000
1'
#2880000
0'
#2900000
1'
#2920000
0'
#2940000
1'
#2960000
0'
#2980000
1'
#3000000
0'
#3020000
b10011001 %
b10011001 2
b10011001 6
1!
b11001100 #
b11111111 "
b11111111 0
b11111111 8
b10011001 1
b10011001 5
1-
b11111111 +
b11111111 /
b11111111 4
1'
b1 :
b1111000 &
b1111000 .
b1111000 3
b1111000 9
#3040000
0'
#3060000
b10111111 #
b11100110 "
b11100110 0
b11100110 8
b10 :
b11100110 +
b11100110 /
b11100110 4
1'
#3080000
0'
#3100000
b10110011 #
b11001101 "
b11001101 0
b11001101 8
b11 :
b11001101 +
b11001101 /
b11001101 4
1'
#3120000
0'
#3140000
b10100110 #
b10110100 "
b10110100 0
b10110100 8
b100 :
b10110100 +
b10110100 /
b10110100 4
1'
#3160000
0'
#3180000
b10011010 #
b10011011 "
b10011011 0
b10011011 8
b101 :
b10011011 +
b10011011 /
b10011011 4
1'
#3200000
0'
#3220000
b10001101 #
b0 "
b0 0
b0 8
b110 :
b10000010 +
b10000010 /
b10000010 4
1'
#3240000
0'
#3260000
b10000001 #
b111 :
b1101001 +
b1101001 /
b1101001 4
1'
#3280000
0'
#3300000
b1110100 #
b1000 :
b1010000 +
b1010000 /
b1010000 4
1'
#3320000
0'
#3340000
b1101000 #
b1001 :
b110111 +
b110111 /
b110111 4
1'
#3360000
0'
#3380000
0!
b1011011 #
0-
b1010 :
b11110 +
b11110 /
b11110 4
1'
#3400000
0'
#3420000
1'
#3440000
0'
#3460000
1'
#3480000
0'
#3500000
1'
#3520000
0'
#3540000
1'
#3560000
0'
#3580000
b10000100 %
b10000100 2
b10000100 6
1!
b11000001 #
b11111111 "
b11111111 0
b11111111 8
b10000100 1
b10000100 5
1-
b11111111 +
b11111111 /
b11111111 4
1'
b1 :
b1101000 &
b1101000 .
b1101000 3
b1101000 9
#3600000
0'
#3620000
b10110101 #
b11100110 "
b11100110 0
b11100110 8
b10 :
b11100110 +
b11100110 /
b11100110 4
1'
#3640000
0'
#3660000
b10101000 #
b11001101 "
b11001101 0
b11001101 8
b11 :
b11001101 +
b11001101 /
b11001101 4
1'
#3680000
0'
#3700000
b10011100 #
b10110100 "
b10110100 0
b10110100 8
b100 :
b10110100 +
b10110100 /
b10110100 4
1'
#3720000
0'
#3740000
b10001111 #
b10011011 "
b10011011 0
b10011011 8
b101 :
b10011011 +
b10011011 /
b10011011 4
1'
#3760000
0'
#3780000
b10000011 #
b0 "
b0 0
b0 8
b110 :
b10000010 +
b10000010 /
b10000010 4
1'
#3800000
0'
#3820000
b1110110 #
b111 :
b1101001 +
b1101001 /
b1101001 4
1'
#3840000
0'
#3860000
b1101010 #
b1000 :
b1010000 +
b1010000 /
b1010000 4
1'
#3880000
0'
#3900000
b1011101 #
b1001 :
b110111 +
b110111 /
b110111 4
1'
#3920000
0'
#3940000
0!
b1010001 #
0-
b1010 :
b11110 +
b11110 /
b11110 4
1'
#3960000
0'
#3980000
1'
#4000000
0'
#4020000
1'
#4040000
0'
#4060000
1'
#4080000
0'
#4100000
1'
#4120000
0'
#4140000
b1110000 %
b1110000 2
b1110000 6
1!
b10110111 #
b11111111 "
b11111111 0
b11111111 8
b1110000 1
b1110000 5
1-
b11111111 +
b11111111 /
b11111111 4
1'
b1 :
b1011000 &
b1011000 .
b1011000 3
b1011000 9
#4160000
0'
#4180000
b10101011 #
b11100110 "
b11100110 0
b11100110 8
b10 :
b11100110 +
b11100110 /
b11100110 4
1'
#4200000
0'
#4220000
b10011110 #
b11001101 "
b11001101 0
b11001101 8
b11 :
b11001101 +
b11001101 /
b11001101 4
1'
#4240000
0'
#4260000
b10010010 #
b10110100 "
b10110100 0
b10110100 8
b100 :
b10110100 +
b10110100 /
b10110100 4
1'
#4280000
0'
#4300000
b10000101 #
b10011011 "
b10011011 0
b10011011 8
b101 :
b10011011 +
b10011011 /
b10011011 4
1'
#4320000
0'
#4340000
b1111001 #
b10000010 "
b10000010 0
b10000010 8
b110 :
b10000010 +
b10000010 /
b10000010 4
1'
#4360000
0'
#4380000
b1101100 #
b0 "
b0 0
b0 8
b111 :
b1101001 +
b1101001 /
b1101001 4
1'
#4400000
0'
#4420000
b1100000 #
b1000 :
b1010000 +
b1010000 /
b1010000 4
1'
#4440000
0'
#4460000
b1010011 #
b1001 :
b110111 +
b110111 /
b110111 4
1'
#4480000
0'
#4500000
0!
b1000111 #
0-
b1010 :
b11110 +
b11110 /
b11110 4
1'
#4520000
0'
#4540000
1'
#4560000
0'
#4580000
1'
#4600000
0'
#4620000
1'
#4640000
0'
#4660000
1'
#4680000
0'
#4700000
b1011011 %
b1011011 2
b1011011 6
1!
b10101101 #
b11111111 "
b11111111 0
b11111111 8
b1011011 1
b1011011 5
1-
b11111111 +
b11111111 /
b11111111 4
1'
b1 :
b1001000 &
b1001000 .
b1001000 3
b1001000 9
#4720000
0'
#4740000
b10100000 #
b11100110 "
b11100110 0
b11100110 8
b10 :
b11100110 +
b11100110 /
b11100110 4
1'
#4760000
0'
#4780000
b10010100 #
b11001101 "
b11001101 0
b11001101 8
b11 :
b11001101 +
b11001101 /
b11001101 4
1'
#4800000
0'
#4820000
b10000111 #
b10110100 "
b10110100 0
b10110100 8
b100 :
b10110100 +
b10110100 /
b10110100 4
1'
#4840000
0'
#4860000
b1111011 #
b10011011 "
b10011011 0
b10011011 8
b101 :
b10011011 +
b10011011 /
b10011011 4
1'
#4880000
0'
#4900000
b1101110 #
b10000010 "
b10000010 0
b10000010 8
b110 :
b10000010 +
b10000010 /
b10000010 4
1'
#4920000
0'
#4940000
b1100010 #
b1101001 "
b1101001 0
b1101001 8
b111 :
b1101001 +
b1101001 /
b1101001 4
1'
#4960000
0'
#4980000
b1010101 #
b0 "
b0 0
b0 8
b1000 :
b1010000 +
b1010000 /
b1010000 4
1'
#5000000
0'
#5020000
b1001001 #
b1001 :
b110111 +
b110111 /
b110111 4
1'
#5040000
0'
#5060000
0!
b111100 #
0-
b1010 :
b11110 +
b11110 /
b11110 4
1'
#5080000
0'
#5100000
1'
#5120000
0'
#5140000
1'
#5160000
0'
#5180000
1'
#5200000
0'
#5220000
1'
#5240000
0'
#5260000
b1000111 %
b1000111 2
b1000111 6
1!
b10100011 #
b11111111 "
b11111111 0
b11111111 8
b1000111 1
b1000111 5
1-
b11111111 +
b11111111 /
b11111111 4
1'
b1 :
b111000 &
b111000 .
b111000 3
b111000 9
#5280000
0'
#5300000
b10010110 #
b11100110 "
b11100110 0
b11100110 8
b10 :
b11100110 +
b11100110 /
b11100110 4
1'
#5320000
0'
#5340000
b10001010 #
b11001101 "
b11001101 0
b11001101 8
b11 :
b11001101 +
b11001101 /
b11001101 4
1'
#5360000
0'
#5380000
b1111101 #
b10110100 "
b10110100 0
b10110100 8
b100 :
b10110100 +
b10110100 /
b10110100 4
1'
#5400000
0'
#5420000
b1110001 #
b10011011 "
b10011011 0
b10011011 8
b101 :
b10011011 +
b10011011 /
b10011011 4
1'
#5440000
0'
#5460000
b1100100 #
b10000010 "
b10000010 0
b10000010 8
b110 :
b10000010 +
b10000010 /
b10000010 4
1'
#5480000
0'
#5500000
b1011000 #
b1101001 "
b1101001 0
b1101001 8
b111 :
b1101001 +
b1101001 /
b1101001 4
1'
#5520000
0'
#5540000
b1001011 #
b1010000 "
b1010000 0
b1010000 8
b1000 :
b1010000 +
b1010000 /
b1010000 4
1'
#5560000
0'
#5580000
b111111 #
b0 "
b0 0
b0 8
b1001 :
b110111 +
b110111 /
b110111 4
1'
#5600000
0'
#5620000
0!
b110010 #
0-
b1010 :
b11110 +
b11110 /
b11110 4
1'
#5640000
0'
#5660000
1'
#5680000
0'
#5700000
1'
#5720000
0'
#5740000
1'
#5760000
0'
#5780000
1'
#5800000
0'
#5820000
b11111111 %
b11111111 2
b11111111 6
1!
b11111111 #
b11111111 "
b11111111 0
b11111111 8
b11111111 7
b11111111 1
b11111111 5
b1 <
1-
b11111111 +
b11111111 /
b11111111 4
1'
b11001000 ;
b11001000 &
b11001000 .
b11001000 3
1)
b101000 9
#5840000
0'
#5860000
b11110010 #
b11110010 "
b11110010 0
b11110010 8
b11110010 7
b10 <
b11100110 +
b11100110 /
b11100110 4
1'
#5880000
0'
#5900000
b11100110 #
b11100110 "
b11100110 0
b11100110 8
b11100110 7
b11 <
b11001101 +
b11001101 /
b11001101 4
1'
#5920000
0'
#5940000
b11011001 #
b11011001 "
b11011001 0
b11011001 8
b11011001 7
b100 <
b10110100 +
b10110100 /
b10110100 4
1'
#5960000
0'
#5980000
b11001101 #
b11001101 "
b11001101 0
b11001101 8
b11001101 7
b101 <
b10011011 +
b10011011 /
b10011011 4
1'
#6000000
0'
#6020000
b11000000 #
b11000000 "
b11000000 0
b11000000 8
b11000000 7
b110 <
b10000010 +
b10000010 /
b10000010 4
1'
#6040000
0'
#6060000
b10110100 #
b10110100 "
b10110100 0
b10110100 8
b10110100 7
b111 <
b1101001 +
b1101001 /
b1101001 4
1'
#6080000
0'
#6100000
b10100111 #
b10100111 "
b10100111 0
b10100111 8
b10100111 7
b1000 <
b1010000 +
b1010000 /
b1010000 4
1'
#6120000
0'
#6140000
b10011011 #
b10011011 "
b10011011 0
b10011011 8
b10011011 7
b1001 <
b110111 +
b110111 /
b110111 4
1'
#6160000
0'
#6180000
0!
b10001110 #
b0 "
b0 0
b0 8
0-
b1010 <
b11110 +
b11110 /
b11110 4
1'
#6200000
0'
#6220000
1'
#6240000
0'
#6260000
1'
#6280000
0'
#6300000
1'
#6320000
0'
#6340000
1'
#6360000
0'
#6380000
b11101011 %
b11101011 2
b11101011 6
1!
b11110101 #
b11110101 "
b11110101 0
b11110101 8
b11110101 7
b11101011 1
b11101011 5
1-
b11111111 +
b11111111 /
b11111111 4
1'
b1 <
b10111000 &
b10111000 .
b10111000 3
b10111000 ;
#6400000
0'
#6420000
b11101000 #
b11101000 "
b11101000 0
b11101000 8
b11101000 7
b10 <
b11100110 +
b11100110 /
b11100110 4
1'
#6440000
0'
#6460000
b11011100 #
b11011100 "
b11011100 0
b11011100 8
b11011100 7
b11 <
b11001101 +
b11001101 /
b11001101 4
1'
#6480000
0'
#6500000
b11001111 #
b11001111 "
b11001111 0
b11001111 8
b11001111 7
b100 <
b10110100 +
b10110100 /
b10110100 4
1'
#6520000
0'
#6540000
b11000011 #
b11000011 "
b11000011 0
b11000011 8
b11000011 7
b101 <
b10011011 +
b10011011 /
b10011011 4
1'
#6560000
0'
#6580000
b10110110 #
b10110110 "
b10110110 0
b10110110 8
b10110110 7
b110 <
b10000010 +
b10000010 /
b10000010 4
1'
#6600000
0'
#6620000
b10101010 #
b10101010 "
b10101010 0
b10101010 8
b10101010 7
b111 <
b1101001 +
b1101001 /
b1101001 4
1'
#6640000
0'
#6660000
b10011101 #
b10011101 "
b10011101 0
b10011101 8
b10011101 7
b1000 <
b1010000 +
b1010000 /
b1010000 4
1'
#6680000
0'
#6700000
b10010001 #
b10010001 "
b10010001 0
b10010001 8
b10010001 7
b1001 <
b110111 +
b110111 /
b110111 4
1'
#6720000
0'
#6740000
0!
b10000100 #
b0 "
b0 0
b0 8
0-
b1010 <
b11110 +
b11110 /
b11110 4
1'
#6760000
0'
#6780000
1'
#6800000
0'
#6820000
1'
#6840000
0'
#6860000
1'
#6880000
0'
#6900000
1'
#6920000
0'
#6940000
b11010110 %
b11010110 2
b11010110 6
1!
b11101010 #
b11101010 "
b11101010 0
b11101010 8
b11101010 7
b11010110 1
b11010110 5
1-
b11111111 +
b11111111 /
b11111111 4
1'
b1 <
b10101000 &
b10101000 .
b10101000 3
b10101000 ;
#6960000
0'
#6980000
b11011110 #
b11011110 "
b11011110 0
b11011110 8
b11011110 7
b10 <
b11100110 +
b11100110 /
b11100110 4
1'
#7000000
0'
#7020000
b11010001 #
b11010001 "
b11010001 0
b11010001 8
b11010001 7
b11 <
b11001101 +
b11001101 /
b11001101 4
1'
#7040000
0'
#7060000
b11000101 #
b11000101 "
b11000101 0
b11000101 8
b11000101 7
b100 <
b10110100 +
b10110100 /
b10110100 4
1'
#7080000
0'
#7100000
b10111000 #
b10111000 "
b10111000 0
b10111000 8
b10111000 7
b101 <
b10011011 +
b10011011 /
b10011011 4
1'
#7120000
0'
#7140000
b10101100 #
b10101100 "
b10101100 0
b10101100 8
b10101100 7
b110 <
b10000010 +
b10000010 /
b10000010 4
1'
#7160000
0'
#7180000
b10011111 #
b10011111 "
b10011111 0
b10011111 8
b10011111 7
b111 <
b1101001 +
b1101001 /
b1101001 4
1'
#7200000
0'
#7220000
b10010011 #
b10010011 "
b10010011 0
b10010011 8
b10010011 7
b1000 <
b1010000 +
b1010000 /
b1010000 4
1'
#7240000
0'
#7260000
b10000110 #
b10000110 "
b10000110 0
b10000110 8
b10000110 7
b1001 <
b110111 +
b110111 /
b110111 4
1'
#7280000
0'
#7300000
0!
b1111010 #
b0 "
b0 0
b0 8
0-
b1010 <
b11110 +
b11110 /
b11110 4
1'
#7320000
0'
#7340000
1'
#7360000
0'
#7380000
1'
#7400000
0'
#7420000
1'
#7440000
0'
#7460000
1'
#7480000
0'
#7500000
b11000010 %
b11000010 2
b11000010 6
1!
b11100000 #
b11100000 "
b11100000 0
b11100000 8
b11100000 7
b11000010 1
b11000010 5
1-
b11111111 +
b11111111 /
b11111111 4
1'
b1 <
b10011000 &
b10011000 .
b10011000 3
b10011000 ;
#7520000
0'
#7540000
b11010100 #
b11010100 "
b11010100 0
b11010100 8
b11010100 7
b10 <
b11100110 +
b11100110 /
b11100110 4
1'
#7560000
0'
#7580000
b11000111 #
b11000111 "
b11000111 0
b11000111 8
b11000111 7
b11 <
b11001101 +
b11001101 /
b11001101 4
1'
#7600000
0'
#7620000
b10111011 #
b10111011 "
b10111011 0
b10111011 8
b10111011 7
b100 <
b10110100 +
b10110100 /
b10110100 4
1'
#7640000
0'
#7660000
b10101110 #
b10101110 "
b10101110 0
b10101110 8
b10101110 7
b101 <
b10011011 +
b10011011 /
b10011011 4
1'
#7680000
0'
#7700000
b10100010 #
b10100010 "
b10100010 0
b10100010 8
b10100010 7
b110 <
b10000010 +
b10000010 /
b10000010 4
1'
#7720000
0'
#7740000
b10010101 #
b10010101 "
b10010101 0
b10010101 8
b10010101 7
b111 <
b1101001 +
b1101001 /
b1101001 4
1'
#7760000
0'
#7780000
b10001001 #
b10001001 "
b10001001 0
b10001001 8
b10001001 7
b1000 <
b1010000 +
b1010000 /
b1010000 4
1'
#7800000
0'
#7820000
b1111100 #
b1111100 "
b1111100 0
b1111100 8
b1111100 7
b1001 <
b110111 +
b110111 /
b110111 4
1'
#7840000
0'
#7860000
0!
b1110000 #
b0 "
b0 0
b0 8
0-
b1010 <
b11110 +
b11110 /
b11110 4
1'
#7880000
0'
#7900000
1'
#7920000
0'
#7940000
1'
#7960000
0'
#7980000
1'
#8000000
0'
#8020000
1'
#8040000
0'
#8060000
b10101101 %
b10101101 2
b10101101 6
1!
b11010110 #
b11010110 "
b11010110 0
b11010110 8
b11010110 7
b10101101 1
b10101101 5
1-
b11111111 +
b11111111 /
b11111111 4
1'
b1 <
b10001000 &
b10001000 .
b10001000 3
b10001000 ;
#8080000
0'
#8100000
b11001001 #
b11001001 "
b11001001 0
b11001001 8
b11001001 7
b10 <
b11100110 +
b11100110 /
b11100110 4
1'
#8120000
0'
#8140000
b10111101 #
b10111101 "
b10111101 0
b10111101 8
b10111101 7
b11 <
b11001101 +
b11001101 /
b11001101 4
1'
#8160000
0'
