Pixel Wise Filters Parallel/brightness_filter.sv
`timescale 1ns/1ps

// Brightness filter module
// Adds scaled brightness to pixel and averages.

module brightness_filter 
#(
    parameter int BITS         = 8,   // pixel bit depth
    parameter int MAX_BPM      = 200,
    parameter int STEP_SIZE    = (256 * (1<<8)) / 200
)
(
    input  logic                  clk,
    input  logic                  reset,

    input  logic [BITS-1:0]       pix_in,       
    input  logic                  valid_in,
    output logic                  module_ready,

    input  logic                  filter_enable,
    input  logic [$clog2(MAX_BPM+1)-1:0] BPM_estimate, 

    output logic [BITS-1:0]       pix_out,
    input  logic                  output_ready,
    output logic                  valid_out,
    output logic [BITS-1:0]       brightness,
    output logic [23:0]           brightness_mult
);

assign module_ready = output_ready;

logic [BITS:0] pix_bright_addition;

// Scale brightness based on BPM
assign brightness_mult = (STEP_SIZE * BPM_estimate) >> 8;
assign brightness      = (brightness_mult > 255) ? 8'd255 : brightness_mult[7:0];

always_comb begin
    if (module_ready && valid_in && filter_enable) begin
        // additive / averaging
        pix_bright_addition = (pix_in + brightness) >> 1;
        pix_out = pix_bright_addition;
    end else begin
        pix_out = 0;
    end
end

assign valid_out = module_ready && valid_in && filter_enable;

endmodule

Pixel Wise Filters Parallel/threshold_filter.sv
`timescale 1ns/1ps

// Threshold filter module
// Zeroes pixels below brightness threshold.

module threshold_filter 
#(
    parameter int BITS         = 8,   // pixel bit depth
    parameter int MAX_BPM      = 200,
    parameter int STEP_SIZE    = (256 * (1<<8)) / 200
)
(
    input  logic                  clk,
    input  logic                  reset,

    input  logic [BITS-1:0]       pix_in,       
    input  logic                  valid_in,
    output logic                  module_ready,

    input  logic                  filter_enable,
    input  logic [$clog2(MAX_BPM+1)-1:0] BPM_estimate, 

    output logic [BITS-1:0]       pix_out,
    input  logic                  output_ready,
    output logic                  valid_out,
    output logic [BITS-1:0]       brightness,
    output logic [23:0]           brightness_mult
);

assign module_ready = output_ready;

// Scale brightness based on BPM
assign brightness_mult = (STEP_SIZE * BPM_estimate) >> 8;
assign brightness      = (brightness_mult > 255) ? 8'd255 : brightness_mult[7:0];

always_comb begin
    if (module_ready && valid_in && filter_enable) begin
        // threshold
        if (pix_in <= brightness)
            pix_out = 0;
        else
            pix_out = pix_in;
    end else begin
        pix_out = 0;
    end
end

assign valid_out = module_ready && valid_in && filter_enable;

endmodule

Pixel Wise Filters Parallel/top_level_filters.sv
`timescale 1ns/1ps

// Top-level wrapper that instantiates brightness_filter and threshold_filter
// Both filters run in parallel. Outputs and ready signals are exposed separately.

module top_level_filters (
    input  logic        clk,
    input  logic        reset,
    input  logic [7:0]  pix_in,
    input  logic        valid_in,
    input  logic        filter_enable,
    input  logic [7:0]  BPM_estimate,
    input  logic        output_ready,

    // Outputs from threshold filter
    output logic [7:0]  pix_out_thresh,
    output logic        valid_out_thresh,
    output logic [7:0]  brightness_thresh,
    output logic        module_ready_thresh,

    // Outputs from brightness filter
    output logic [7:0]  pix_out_bright,
    output logic        valid_out_bright,
    output logic [7:0]  brightness_bright,
    output logic        module_ready_bright
);

  logic [23:0] brightness_mult_thresh;
  logic [23:0] brightness_mult_bright;

  // --- Threshold filter instance ---
  threshold_filter #(
    .BITS(8),
    .MAX_BPM(200)
  ) u_threshold_filter (
    .clk(clk),
    .reset(reset),
    .pix_in(pix_in),
    .valid_in(valid_in),
    .module_ready(module_ready_thresh),
    .filter_enable(filter_enable),
    .BPM_estimate(BPM_estimate),
    .pix_out(pix_out_thresh),
    .output_ready(output_ready),
    .valid_out(valid_out_thresh),
    .brightness(brightness_thresh),
    .brightness_mult(brightness_mult_thresh)
  );

  // --- Brightness filter instance ---
  brightness_filter #(
    .BITS(8),
    .MAX_BPM(200)
  ) u_brightness_filter (
    .clk(clk),
    .reset(reset),
    .pix_in(pix_in),
    .valid_in(valid_in),
    .module_ready(module_ready_bright),
    .filter_enable(filter_enable),
    .BPM_estimate(BPM_estimate),
    .pix_out(pix_out_bright),
    .output_ready(output_ready),
    .valid_out(valid_out_bright),
    .brightness(brightness_bright),
    .brightness_mult(brightness_mult_bright)
  );

endmodule

Pixel Wise Filters Parallel/parallel_pixel_wise_filters_tb.sv
`timescale 1ns/1ps

// ===========================================================
// Testbench for top_level_filters
// Demonstrates: 
//  - Clock + reset generation
//  - DUT instantiation
//  - Stimulus driving (pix_in, BPM)
//  - Output monitoring with $display
//  - VCD dumping for GTKWave (viewing waveforms)
// ===========================================================

module parallel_pixel_wise_filters_tb;

  // ------------------------------
  // Clock & Reset
  // ------------------------------
  logic clk = 0;
  logic reset = 1;

  // Clock generator (25 MHz -> 40ns period)
  always #20 clk = ~clk;

  // Reset pulse
  initial begin
    repeat(5) @(posedge clk);
    reset = 0;
  end

  // ------------------------------
  // DUT connections
  // ------------------------------
  logic [7:0] pix_in;
  logic       valid_in;
  logic       filter_enable;
  logic [7:0] BPM_estimate;
  logic       output_ready;

  // Threshold outputs
  logic [7:0] pix_out_thresh;
  logic       valid_out_thresh;
  logic [7:0] brightness_thresh;
  logic       module_ready_thresh;

  // Brightness outputs
  logic [7:0] pix_out_bright;
  logic       valid_out_bright;
  logic [7:0] brightness_bright;
  logic       module_ready_bright;

  logic [23:0] pix_bright_addition;

  // Instantiate the design under test
  top_level_filters dut (
    .clk(clk),
    .reset(reset),
    .pix_in(pix_in),
    .valid_in(valid_in),
    .filter_enable(filter_enable),
    .BPM_estimate(BPM_estimate),
    .output_ready(output_ready),

    // Threshold outputs
    .pix_out_thresh(pix_out_thresh),
    .valid_out_thresh(valid_out_thresh),
    .brightness_thresh(brightness_thresh),
    .module_ready_thresh(module_ready_thresh),

    // Brightness outputs
    .pix_out_bright(pix_out_bright),
    .valid_out_bright(valid_out_bright),
    .brightness_bright(brightness_bright),
    .module_ready_bright(module_ready_bright)
  );

  // ------------------------------
  // Stimulus
  // ------------------------------
  initial begin
    // Default values
    pix_in        = 0;
    valid_in      = 0;
    filter_enable = 1;
    BPM_estimate  = 200;
    output_ready  = 1;

    // Wait until reset is released
    @(negedge reset);

    // Sweep pixels down and adjust BPM mid-stream
    for (int bpm = 200; bpm >= 56; bpm -= 16) begin
      BPM_estimate = bpm;
      for (int i = 0; i < 10; i++) begin
        @(posedge clk);
        pix_in   <= 255 - i*25;
        valid_in <= 1;
      end
      valid_in <= 0;
      rgba(39, 0, 0, 1);
    end

    #200 $finish;
  end

  // ------------------------------
  // Output Monitoring
  // ------------------------------
  always @(posedge clk) begin
    if (valid_out_thresh || valid_out_bright) begin
      $display("t=%0t | pix_in=%0d | BPM=%0d | Thresh(ready=%0d, bright=%0d, pix_out=%0d, valid=%0d) | Bright(ready=%0d, bright=%0d, avg=%0d, pix_out=%0d, valid=%0d)",
               $time, pix_in, BPM_estimate,
               module_ready_thresh, brightness_thresh, pix_out_thresh, valid_out_thresh,
               module_ready_bright, brightness_bright, pix_bright_addition, pix_out_bright, valid_out_bright);
    end
  end

  assign pix_bright_addition = (pix_in + brightness_bright) >> 1;

  // ------------------------------
  // Waveform Dumping
  // ------------------------------
  initial begin
    $dumpfile("tb.vcd");
    $dumpvars(0, parallel_pixel_wise_filters_tb);
  end

endmodule

Pixel Wise Filters Parallel/tb.vcd
$date
	Thu Sep 25 14:54:03 2025
$end
$version
	Icarus Verilog
$end
$timescale
	1ps
$end
$scope module parallel_pixel_wise_filters_tb $end
$var wire 1 ! valid_out_thresh $end
$var wire 1 " valid_out_bright $end
$var wire 8 # pix_out_thresh [7:0] $end
$var wire 8 $ pix_out_bright [7:0] $end
$var wire 24 % pix_bright_addition [23:0] $end
$var wire 1 & module_ready_thresh $end
$var wire 1 ' module_ready_bright $end
$var wire 8 ( brightness_thresh [7:0] $end
$var wire 8 ) brightness_bright [7:0] $end
$var reg 8 * BPM_estimate [7:0] $end
$var reg 1 + clk $end
$var reg 1 , filter_enable $end
$var reg 1 - output_ready $end
$var reg 8 . pix_in [7:0] $end
$var reg 1 / reset $end
$var reg 1 0 valid_in $end
$scope module dut $end
$var wire 8 1 BPM_estimate [7:0] $end
$var wire 1 + clk $end
$var wire 1 , filter_enable $end
$var wire 1 - output_ready $end
$var wire 8 2 pix_in [7:0] $end
$var wire 1 / reset $end
$var wire 1 0 valid_in $end
$var wire 1 ! valid_out_thresh $end
$var wire 1 " valid_out_bright $end
$var wire 8 3 pix_out_thresh [7:0] $end
$var wire 8 4 pix_out_bright [7:0] $end
$var wire 1 & module_ready_thresh $end
$var wire 1 ' module_ready_bright $end
$var wire 8 5 brightness_thresh [7:0] $end
$var wire 24 6 brightness_mult_thresh [23:0] $end
$var wire 24 7 brightness_mult_bright [23:0] $end
$var wire 8 8 brightness_bright [7:0] $end
$scope module u_brightness_filter $end
$var wire 8 9 BPM_estimate [7:0] $end
$var wire 1 + clk $end
$var wire 1 , filter_enable $end
$var wire 1 ' module_ready $end
$var wire 1 - output_ready $end
$var wire 8 : pix_in [7:0] $end
$var wire 1 / reset $end
$var wire 1 0 valid_in $end
$var wire 1 " valid_out $end
$var wire 24 ; brightness_mult [23:0] $end
$var wire 8 < brightness [7:0] $end
$var reg 9 = pix_bright_addition [8:0] $end
$var reg 8 > pix_out [7:0] $end
$upscope $end
$scope module u_threshold_filter $end
$var wire 8 ? BPM_estimate [7:0] $end
$var wire 1 + clk $end
$var wire 1 , filter_enable $end
$var wire 1 & module_ready $end
$var wire 1 - output_ready $end
$var wire 8 @ pix_in [7:0] $end
$var wire 1 / reset $end
$var wire 1 0 valid_in $end
$var wire 1 ! valid_out $end
$var wire 24 A brightness_mult [23:0] $end
$var wire 8 B brightness [7:0] $end
$var reg 8 C pix_out [7:0] $end
$upscope $end
$upscope $end
$scope begin $ivl_for_loop0 $end
$var integer 32 D bpm [31:0] $end
$scope begin $ivl_for_loop1 $end
$var integer 32 E i [31:0] $end
$upscope $end
$upscope $end
$upscope $end
$enddefinitions $end
#0
$dumpvars
b0 E
b0 D
b0 C
b11111111 B
b11111111 A
b0 @
b11001000 ?
b0 >
bx =
b11111111 <
b11111111 ;
b0 :
b11001000 9
b11111111 8
b11111111 7
b11111111 6
b11111111 5
b0 4
b0 3
b0 2
b11001000 1
00
1/
b0 .
1-
1,
0+
b11001000 *
b11111111 )
b11111111 (
1'
1&
b1111111 %
b0 $
b0 #
0"
0!
$end
#20000
1+
#40000
0+
#60000
1+
#80000
0+
#100000
1+
#120000
0+
#140000
1+
#160000
0+
#180000
b11001000 D
0/
1+
#200000
0+
#220000
1"
1!
b11111111 %
b11111111 $
b11111111 4
b11111111 >
b11111111 =
10
b11111111 .
b11111111 2
b11111111 :
b11111111 @
b1 E
1+
#240000
0+
#260000
b11110010 %
b11110010 $
b11110010 4
b11110010 >
b11110010 =
b11100110 .
b11100110 2
b11100110 :
b11100110 @
b10 E
1+
#280000
0+
#300000
b11100110 %
b11100110 $
b11100110 4
b11100110 >
b11100110 =
b11001101 .
b11001101 2
b11001101 :
b11001101 @
b11 E
1+
#320000
0+
#340000
b11011001 %
b11011001 $
b11011001 4
b11011001 >
b11011001 =
b10110100 .
b10110100 2
b10110100 :
b10110100 @
b100 E
1+
#360000
0+
#380000
b11001101 %
b11001101 $
b11001101 4
b11001101 >
b11001101 =
b10011011 .
b10011011 2
b10011011 :
b10011011 @
b101 E
1+
#400000
0+
#420000
b11000000 %
b11000000 $
b11000000 4
b11000000 >
b11000000 =
b10000010 .
b10000010 2
b10000010 :
b10000010 @
b110 E
1+
#440000
0+
#460000
b10110100 %
b10110100 $
b10110100 4
b10110100 >
b10110100 =
b1101001 .
b1101001 2
b1101001 :
b1101001 @
b111 E
1+
#480000
0+
#500000
b10100111 %
b10100111 $
b10100111 4
b10100111 >
b10100111 =
b1010000 .
b1010000 2
b1010000 :
b1010000 @
b1000 E
1+
#520000
0+
#540000
b10011011 %
b10011011 $
b10011011 4
b10011011 >
b10011011 =
b110111 .
b110111 2
b110111 :
b110111 @
b1001 E
1+
#560000
0+
#580000
0"
0!
b10001110 %
b0 $
b0 4
b0 >
00
b11110 .
b11110 2
b11110 :
b11110 @
b1010 E
1+
#600000
0+
#620000
1+
#640000
0+
#660000
1+
#680000
0+
#700000
1+
#720000
0+
#740000
1+
#760000
0+
#780000
1"
1!
b11110101 $
b11110101 4
b11110101 >
b11110101 =
b11111111 #
b11111111 3
b11111111 C
10
b11111111 .
b11111111 2
b11111111 :
b11111111 @
b11110101 %
b11101011 )
b11101011 8
b11101011 <
b11101011 (
b11101011 5
b11101011 B
b11101011 7
b11101011 ;
b11101011 6
b11101011 A
1+
b1 E
b10111000 *
b10111000 1
b10111000 9
b10111000 ?
b10111000 D
#800000
0+
#820000
b11101000 %
b11101000 $
b11101000 4
b11101000 >
b11101000 =
b0 #
b0 3
b0 C
b11100110 .
b11100110 2
b11100110 :
b11100110 @
b10 E
1+
#840000
0+
#860000
b11011100 %
b11011100 $
b11011100 4
b11011100 >
b11011100 =
b11001101 .
b11001101 2
b11001101 :
b11001101 @
b11 E
1+
#880000
0+
#900000
b11001111 %
b11001111 $
b11001111 4
b11001111 >
b11001111 =
b10110100 .
b10110100 2
b10110100 :
b10110100 @
b100 E
1+
#920000
0+
#940000
b11000011 %
b11000011 $
b11000011 4
b11000011 >
b11000011 =
b10011011 .
b10011011 2
b10011011 :
b10011011 @
b101 E
1+
#960000
0+
#980000
b10110110 %
b10110110 $
b10110110 4
b10110110 >
b10110110 =
b10000010 .
b10000010 2
b10000010 :
b10000010 @
b110 E
1+
#1000000
0+
#1020000
b10101010 %
b10101010 $
b10101010 4
b10101010 >
b10101010 =
b1101001 .
b1101001 2
b1101001 :
b1101001 @
b111 E
1+
#1040000
0+
#1060000
b10011101 %
b10011101 $
b10011101 4
b10011101 >
b10011101 =
b1010000 .
b1010000 2
b1010000 :
b1010000 @
b1000 E
1+
#1080000
0+
#1100000
b10010001 %
b10010001 $
b10010001 4
b10010001 >
b10010001 =
b110111 .
b110111 2
b110111 :
b110111 @
b1001 E
1+
#1120000
0+
#1140000
0"
0!
b10000100 %
b0 $
b0 4
b0 >
00
b11110 .
b11110 2
b11110 :
b11110 @
b1010 E
1+
#1160000
0+
#1180000
1+
#1200000
0+
#1220000
1+
#1240000
0+
#1260000
1+
#1280000
0+
#1300000
1+
#1320000
0+
#1340000
1"
1!
b11101010 $
b11101010 4
b11101010 >
b11101010 =
b11111111 #
b11111111 3
b11111111 C
10
b11111111 .
b11111111 2
b11111111 :
b11111111 @
b11101010 %
b11010110 )
b11010110 8
b11010110 <
b11010110 (
b11010110 5
b11010110 B
b11010110 7
b11010110 ;
b11010110 6
b11010110 A
1+
b1 E
b10101000 *
b10101000 1
b10101000 9
b10101000 ?
b10101000 D
#1360000
0+
#1380000
b11011110 %
b11011110 $
b11011110 4
b11011110 >
b11011110 =
b11100110 #
b11100110 3
b11100110 C
b11100110 .
b11100110 2
b11100110 :
b11100110 @
b10 E
1+
#1400000
0+
#1420000
b11010001 %
b11010001 $
b11010001 4
b11010001 >
b11010001 =
b0 #
b0 3
b0 C
b11001101 .
b11001101 2
b11001101 :
b11001101 @
b11 E
1+
#1440000
0+
#1460000
b11000101 %
b11000101 $
b11000101 4
b11000101 >
b11000101 =
b10110100 .
b10110100 2
b10110100 :
b10110100 @
b100 E
1+
#1480000
0+
#1500000
b10111000 %
b10111000 $
b10111000 4
b10111000 >
b10111000 =
b10011011 .
b10011011 2
b10011011 :
b10011011 @
b101 E
1+
#1520000
0+
#1540000
b10101100 %
b10101100 $
b10101100 4
b10101100 >
b10101100 =
b10000010 .
b10000010 2
b10000010 :
b10000010 @
b110 E
1+
#1560000
0+
#1580000
b10011111 %
b10011111 $
b10011111 4
b10011111 >
b10011111 =
b1101001 .
b1101001 2
b1101001 :
b1101001 @
b111 E
1+
#1600000
0+
#1620000
b10010011 %
b10010011 $
b10010011 4
b10010011 >
b10010011 =
b1010000 .
b1010000 2
b1010000 :
b1010000 @
b1000 E
1+
#1640000
0+
#1660000
b10000110 %
b10000110 $
b10000110 4
b10000110 >
b10000110 =
b110111 .
b110111 2
b110111 :
b110111 @
b1001 E
1+
#1680000
0+
#1700000
0"
0!
b1111010 %
b0 $
b0 4
b0 >
00
b11110 .
b11110 2
b11110 :
b11110 @
b1010 E
1+
#1720000
0+
#1740000
1+
#1760000
0+
#1780000
1+
#1800000
0+
#1820000
1+
#1840000
0+
#1860000
1+
#1880000
0+
#1900000
1"
1!
b11100000 $
b11100000 4
b11100000 >
b11100000 =
b11111111 #
b11111111 3
b11111111 C
10
b11111111 .
b11111111 2
b11111111 :
b11111111 @
b11100000 %
b11000010 )
b11000010 8
b11000010 <
b11000010 (
b11000010 5
b11000010 B
b11000010 7
b11000010 ;
b11000010 6
b11000010 A
1+
b1 E
b10011000 *
b10011000 1
b10011000 9
b10011000 ?
b10011000 D
#1920000
0+
#1940000
b11010100 %
b11010100 $
b11010100 4
b11010100 >
b11010100 =
b11100110 #
b11100110 3
b11100110 C
b11100110 .
b11100110 2
b11100110 :
b11100110 @
b10 E
1+
#1960000
0+
#1980000
b11000111 %
b11000111 $
b11000111 4
b11000111 >
b11000111 =
b11001101 #
b11001101 3
b11001101 C
b11001101 .
b11001101 2
b11001101 :
b11001101 @
b11 E
1+
#2000000
0+
#2020000
b10111011 %
b10111011 $
b10111011 4
b10111011 >
b10111011 =
b0 #
b0 3
b0 C
b10110100 .
b10110100 2
b10110100 :
b10110100 @
b100 E
1+
#2040000
0+
#2060000
b10101110 %
b10101110 $
b10101110 4
b10101110 >
b10101110 =
b10011011 .
b10011011 2
b10011011 :
b10011011 @
b101 E
1+
#2080000
0+
#2100000
b10100010 %
b10100010 $
b10100010 4
b10100010 >
b10100010 =
b10000010 .
b10000010 2
b10000010 :
b10000010 @
b110 E
1+
#2120000
0+
#2140000
b10010101 %
b10010101 $
b10010101 4
b10010101 >
b10010101 =
b1101001 .
b1101001 2
b1101001 :
b1101001 @
b111 E
1+
#2160000
0+
#2180000
b10001001 %
b10001001 $
b10001001 4
b10001001 >
b10001001 =
b1010000 .
b1010000 2
b1010000 :
b1010000 @
b1000 E
1+
#2200000
0+
#2220000
b1111100 %
b1111100 $
b1111100 4
b1111100 >
b1111100 =
b110111 .
b110111 2
b110111 :
b110111 @
b1001 E
1+
#2240000
0+
#2260000
0"
0!
b1110000 %
b0 $
b0 4
b0 >
00
b11110 .
b11110 2
b11110 :
b11110 @
b1010 E
1+
#2280000
0+
#2300000
1+
#2320000
0+
#2340000
1+
#2360000
0+
#2380000
1+
#2400000
0+
#2420000
1+
#2440000
0+
#2460000
1"
1!
b11010110 $
b11010110 4
b11010110 >
b11010110 =
b11111111 #
b11111111 3
b11111111 C
10
b11111111 .
b11111111 2
b11111111 :
b11111111 @
b11010110 %
b10101101 )
b10101101 8
b10101101 <
b10101101 (
b10101101 5
b10101101 B
b10101101 7
b10101101 ;
b10101101 6
b10101101 A
1+
b1 E
b10001000 *
b10001000 1
b10001000 9
b10001000 ?
b10001000 D
#2480000
0+
#2500000
b11001001 %
b11001001 $
b11001001 4
b11001001 >
b11001001 =
b11100110 #
b11100110 3
b11100110 C
b11100110 .
b11100110 2
b11100110 :
b11100110 @
b10 E
1+
#2520000
0+
#2540000
b10111101 %
b10111101 $
b10111101 4
b10111101 >
b10111101 =
b11001101 #
b11001101 3
b11001101 C
b11001101 .
b11001101 2
b11001101 :
b11001101 @
b11 E
1+
#2560000
0+
#2580000
b10110000 %
b10110000 $
b10110000 4
b10110000 >
b10110000 =
b10110100 #
b10110100 3
b10110100 C
b10110100 .
b10110100 2
b10110100 :
b10110100 @
b100 E
1+
#2600000
0+
#2620000
b10100100 %
b10100100 $
b10100100 4
b10100100 >
b10100100 =
b0 #
b0 3
b0 C
b10011011 .
b10011011 2
b10011011 :
b10011011 @
b101 E
1+
#2640000
0+
#2660000
b10010111 %
b10010111 $
b10010111 4
b10010111 >
b10010111 =
b10000010 .
b10000010 2
b10000010 :
b10000010 @
b110 E
1+
#2680000
0+
#2700000
b10001011 %
b10001011 $
b10001011 4
b10001011 >
b10001011 =
b1101001 .
b1101001 2
b1101001 :
b1101001 @
b111 E
1+
#2720000
0+
#2740000
b1111110 %
b1111110 $
b1111110 4
b1111110 >
b1111110 =
b1010000 .
b1010000 2
b1010000 :
b1010000 @
b1000 E
1+
#2760000
0+
#2780000
b1110010 %
b1110010 $
b1110010 4
b1110010 >
b1110010 =
b110111 .
b110111 2
b110111 :
b110111 @
b1001 E
1+
#2800000
0+
#2820000
0"
0!
b1100101 %
b0 $
b0 4
b0 >
00
b11110 .
b11110 2
b11110 :
b11110 @
b1010 E
1+
#2840000
0+
#2860000
1+
#2880000
0+
#2900000
1+
#2920000
0+
#2940000
1+
#2960000
0+
#2980000
1+
#3000000
0+
#3020000
1"
1!
b11001100 $
b11001100 4
b11001100 >
b11001100 =
b11111111 #
b11111111 3
b11111111 C
10
b11111111 .
b11111111 2
b11111111 :
b11111111 @
b11001100 %
b10011001 )
b10011001 8
b10011001 <
b10011001 (
b10011001 5
b10011001 B
b10011001 7
b10011001 ;
b10011001 6
b10011001 A
1+
b1 E
b1111000 *
b1111000 1
b1111000 9
b1111000 ?
b1111000 D
#3040000
0+
#3060000
b10111111 %
b10111111 $
b10111111 4
b10111111 >
b10111111 =
b11100110 #
b11100110 3
b11100110 C
b11100110 .
b11100110 2
b11100110 :
b11100110 @
b10 E
1+
#3080000
0+
#3100000
b10110011 %
b10110011 $
b10110011 4
b10110011 >
b10110011 =
b11001101 #
b11001101 3
b11001101 C
b11001101 .
b11001101 2
b11001101 :
b11001101 @
b11 E
1+
#3120000
0+
#3140000
b10100110 %
b10100110 $
b10100110 4
b10100110 >
b10100110 =
b10110100 #
b10110100 3
b10110100 C
b10110100 .
b10110100 2
b10110100 :
b10110100 @
b100 E
1+
#3160000
0+
#3180000
b10011010 %
b10011010 $
b10011010 4
b10011010 >
b10011010 =
b10011011 #
b10011011 3
b10011011 C
b10011011 .
b10011011 2
b10011011 :
b10011011 @
b101 E
1+
#3200000
0+
#3220000
b10001101 %
b10001101 $
b10001101 4
b10001101 >
b10001101 =
b0 #
b0 3
b0 C
b10000010 .
b10000010 2
b10000010 :
b10000010 @
b110 E
1+
#3240000
0+
#3260000
b10000001 %
b10000001 $
b10000001 4
b10000001 >
b10000001 =
b1101001 .
b1101001 2
b1101001 :
b1101001 @
b111 E
1+
#3280000
0+
#3300000
b1110100 %
b1110100 $
b1110100 4
b1110100 >
b1110100 =
b1010000 .
b1010000 2
b1010000 :
b1010000 @
b1000 E
1+
#3320000
0+
#3340000
b1101000 %
b1101000 $
b1101000 4
b1101000 >
b1101000 =
b110111 .
b110111 2
b110111 :
b110111 @
b1001 E
1+
#3360000
0+
#3380000
0"
0!
b1011011 %
b0 $
b0 4
b0 >
00
b11110 .
b11110 2
b11110 :
b11110 @
b1010 E
1+
#3400000
0+
#3420000
1+
#3440000
0+
#3460000
1+
#3480000
0+
#3500000
1+
#3520000
0+
#3540000
1+
#3560000
0+
#3580000
1"
1!
b11000001 $
b11000001 4
b11000001 >
b11000001 =
b11111111 #
b11111111 3
b11111111 C
10
b11111111 .
b11111111 2
b11111111 :
b11111111 @
b11000001 %
b10000100 )
b10000100 8
b10000100 <
b10000100 (
b10000100 5
b10000100 B
b10000100 7
b10000100 ;
b10000100 6
b10000100 A
1+
b1 E
b1101000 *
b1101000 1
b1101000 9
b1101000 ?
b1101000 D
#3600000
0+
#3620000
b10110101 %
b10110101 $
b10110101 4
b10110101 >
b10110101 =
b11100110 #
b11100110 3
b11100110 C
b11100110 .
b11100110 2
b11100110 :
b11100110 @
b10 E
1+
#3640000
0+
#3660000
b10101000 %
b10101000 $
b10101000 4
b10101000 >
b10101000 =
b11001101 #
b11001101 3
b11001101 C
b11001101 .
b11001101 2
b11001101 :
b11001101 @
b11 E
1+
#3680000
0+
#3700000
b10011100 %
b10011100 $
b10011100 4
b10011100 >
b10011100 =
b10110100 #
b10110100 3
b10110100 C
b10110100 .
b10110100 2
b10110100 :
b10110100 @
b100 E
1+
#3720000
0+
#3740000
b10001111 %
b10001111 $
b10001111 4
b10001111 >
b10001111 =
b10011011 #
b10011011 3
b10011011 C
b10011011 .
b10011011 2
b10011011 :
b10011011 @
b101 E
1+
#3760000
0+
#3780000
b10000011 %
b10000011 $
b10000011 4
b10000011 >
b10000011 =
b0 #
b0 3
b0 C
b10000010 .
b10000010 2
b10000010 :
b10000010 @
b110 E
1+
#3800000
0+
#3820000
b1110110 %
b1110110 $
b1110110 4
b1110110 >
b1110110 =
b1101001 .
b1101001 2
b1101001 :
b1101001 @
b111 E
1+
#3840000
0+
#3860000
b1101010 %
b1101010 $
b1101010 4
b1101010 >
b1101010 =
b1010000 .
b1010000 2
b1010000 :
b1010000 @
b1000 E
1+
#3880000
0+
#3900000
b1011101 %
b1011101 $
b1011101 4
b1011101 >
b1011101 =
b110111 .
b110111 2
b110111 :
b110111 @
b1001 E
1+
#3920000
0+
#3940000
0"
0!
b1010001 %
b0 $
b0 4
b0 >
00
b11110 .
b11110 2
b11110 :
b11110 @
b1010 E
1+
#3960000
0+
#3980000
1+
#4000000
0+
#4020000
1+
#4040000
0+
#4060000
1+
#4080000
0+
#4100000
1+
#4120000
0+
#4140000
1"
1!
b10110111 $
b10110111 4
b10110111 >
b10110111 =
b11111111 #
b11111111 3
b11111111 C
10
b11111111 .
b11111111 2
b11111111 :
b11111111 @
b10110111 %
b1110000 )
b1110000 8
b1110000 <
b1110000 (
b1110000 5
b1110000 B
b1110000 7
b1110000 ;
b1110000 6
b1110000 A
1+
b1 E
b1011000 *
b1011000 1
b1011000 9
b1011000 ?
b1011000 D
#4160000
0+
#4180000
b10101011 %
b10101011 $
b10101011 4
b10101011 >
b10101011 =
b11100110 #
b11100110 3
b11100110 C
b11100110 .
b11100110 2
b11100110 :
b11100110 @
b10 E
1+
#4200000
0+
#4220000
b10011110 %
b10011110 $
b10011110 4
b10011110 >
b10011110 =
b11001101 #
b11001101 3
b11001101 C
b11001101 .
b11001101 2
b11001101 :
b11001101 @
b11 E
1+
#4240000
0+
#4260000
b10010010 %
b10010010 $
b10010010 4
b10010010 >
b10010010 =
b10110100 #
b10110100 3
b10110100 C
b10110100 .
b10110100 2
b10110100 :
b10110100 @
b100 E
1+
#4280000
0+
#4300000
b10000101 %
b10000101 $
b10000101 4
b10000101 >
b10000101 =
b10011011 #
b10011011 3
b10011011 C
b10011011 .
b10011011 2
b10011011 :
b10011011 @
b101 E
1+
#4320000
0+
#4340000
b1111001 %
b1111001 $
b1111001 4
b1111001 >
b1111001 =
b10000010 #
b10000010 3
b10000010 C
b10000010 .
b10000010 2
b10000010 :
b10000010 @
b110 E
1+
#4360000
0+
#4380000
b1101100 %
b1101100 $
b1101100 4
b1101100 >
b1101100 =
b0 #
b0 3
b0 C
b1101001 .
b1101001 2
b1101001 :
b1101001 @
b111 E
1+
#4400000
0+
#4420000
b1100000 %
b1100000 $
b1100000 4
b1100000 >
b1100000 =
b1010000 .
b1010000 2
b1010000 :
b1010000 @
b1000 E
1+
#4440000
0+
#4460000
b1010011 %
b1010011 $
b1010011 4
b1010011 >
b1010011 =
b110111 .
b110111 2
b110111 :
b110111 @
b1001 E
1+
#4480000
0+
#4500000
0"
0!
b1000111 %
b0 $
b0 4
b0 >
00
b11110 .
b11110 2
b11110 :
b11110 @
b1010 E
1+
#4520000
0+
#4540000
1+
#4560000
0+
#4580000
1+
#4600000
0+
#4620000
1+
#4640000
0+
#4660000
1+
#4680000
0+
#4700000
1"
1!
b10101101 $
b10101101 4
b10101101 >
b10101101 =
b11111111 #
b11111111 3
b11111111 C
10
b11111111 .
b11111111 2
b11111111 :
b11111111 @
b10101101 %
b1011011 )
b1011011 8
b1011011 <
b1011011 (
b1011011 5
b1011011 B
b1011011 7
b1011011 ;
b1011011 6
b1011011 A
1+
b1 E
b1001000 *
b1001000 1
b1001000 9
b1001000 ?
b1001000 D
#4720000
0+
#4740000
b10100000 %
b10100000 $
b10100000 4
b10100000 >
b10100000 =
b11100110 #
b11100110 3
b11100110 C
b11100110 .
b11100110 2
b11100110 :
b11100110 @
b10 E
1+
#4760000
0+
#4780000
b10010100 %
b10010100 $
b10010100 4
b10010100 >
b10010100 =
b11001101 #
b11001101 3
b11001101 C
b11001101 .
b11001101 2
b11001101 :
b11001101 @
b11 E
1+
#4800000
0+
#4820000
b10000111 %
b10000111 $
b10000111 4
b10000111 >
b10000111 =
b10110100 #
b10110100 3
b10110100 C
b10110100 .
b10110100 2
b10110100 :
b10110100 @
b100 E
1+
#4840000
0+
#4860000
b1111011 %
b1111011 $
b1111011 4
b1111011 >
b1111011 =
b10011011 #
b10011011 3
b10011011 C
b10011011 .
b10011011 2
b10011011 :
b10011011 @
b101 E
1+
#4880000
0+
#4900000
b1101110 %
b1101110 $
b1101110 4
b1101110 >
b1101110 =
b10000010 #
b10000010 3
b10000010 C
b10000010 .
b10000010 2
b10000010 :
b10000010 @
b110 E
1+
#4920000
0+
#4940000
b1100010 %
b1100010 $
b1100010 4
b1100010 >
b1100010 =
b1101001 #
b1101001 3
b1101001 C
b1101001 .
b1101001 2
b1101001 :
b1101001 @
b111 E
1+
#4960000
0+
#4980000
b1010101 %
b1010101 $
b1010101 4
b1010101 >
b1010101 =
b0 #
b0 3
b0 C
b1010000 .
b1010000 2
b1010000 :
b1010000 @
b1000 E
1+
#5000000
0+
#5020000
b1001001 %
b1001001 $
b1001001 4
b1001001 >
b1001001 =
b110111 .
b110111 2
b110111 :
b110111 @
b1001 E
1+
#5040000
0+
#5060000
0"
0!
b111100 %
b0 $
b0 4
b0 >
00
b11110 .
b11110 2
b11110 :
b11110 @
b1010 E
1+
#5080000
0+
#5100000
1+
#5120000
0+
#5140000
1+
#5160000
0+
#5180000
1+
#5200000
0+
#5220000
1+
#5240000
0+
